{
    "phone": "*",
    "companyOfficers": [],
    "executiveTeam": [],
    "maxAge": 86400,
    "priceHint": 2,
    "previousClose": 86.88,
    "open": 87.59,
    "dayLow": 87.38,
    "dayHigh": 87.86,
    "regularMarketPreviousClose": 86.88,
    "regularMarketOpen": 87.59,
    "regularMarketDayLow": 87.38,
    "regularMarketDayHigh": 87.86,
    "trailingPE": 35.695305,
    "volume": 45306,
    "regularMarketVolume": 45306,
    "averageVolume": 39520,
    "averageVolume10days": 36764,
    "averageDailyVolume10Day": 36764,
    "bid": 0.0,
    "ask": 0.0,
    "bidSize": 0,
    "askSize": 0,
    "yield": 0.0,
    "totalAssets": 885473152,
    "fiftyTwoWeekLow": 59.7,
    "fiftyTwoWeekHigh": 91.1,
    "allTimeHigh": 91.1,
    "allTimeLow": 10.5,
    "fiftyDayAverage": 87.108,
    "twoHundredDayAverage": 81.78368,
    "navPrice": 87.0357,
    "currency": "EUR",
    "tradeable": false,
    "ytdReturn": 6.00786,
    "beta3Year": 0.97,
    "fundFamily": "Amundi Asset Management",
    "fundInceptionDate": 1749081600,
    "legalType": "Exchange Traded Fund",
    "threeYearAverageReturn": 0.2501645,
    "fiveYearAverageReturn": 0.1491484,
    "quoteType": "ETF",
    "symbol": "PUST.PA",
    "language": "en-US",
    "region": "US",
    "typeDisp": "ETF",
    "quoteSourceName": "Delayed Quote",
    "triggerable": false,
    "customPriceAlertConfidence": "LOW",
    "marketState": "REGULAR",
    "corporateActions": [],
    "regularMarketTime": 1769618113,
    "exchange": "PAR",
    "messageBoardId": "finmb_264121047",
    "exchangeTimezoneName": "Europe/Paris",
    "exchangeTimezoneShortName": "CET",
    "gmtOffSetMilliseconds": 3600000,
    "market": "fr_market",
    "esgPopulated": false,
    "regularMarketChangePercent": 0.67910224,
    "regularMarketPrice": 87.47,
    "shortName": "Amundi PEA Nasdaq-100 UCITS ETF",
    "longName": "Amundi PEA Nasdaq-100 UCITS ETF Acc",
    "hasPrePostMarketData": false,
    "firstTradeDateMilliseconds": 1400569200000,
    "regularMarketChange": 0.59000397,
    "regularMarketDayRange": "87.38 - 87.86",
    "fullExchangeName": "Paris",
    "averageDailyVolume3Month": 39520,
    "fiftyTwoWeekLowChange": 27.77,
    "fiftyTwoWeekLowChangePercent": 0.46515912,
    "fiftyTwoWeekRange": "59.7 - 91.1",
    "fiftyTwoWeekHighChange": -3.6299973,
    "fiftyTwoWeekHighChangePercent": -0.039846294,
    "fiftyTwoWeekChangePercent": 5.4880977,
    "dividendYield": 0.0,
    "trailingThreeMonthReturns": 2.35961,
    "trailingThreeMonthNavReturns": 2.35961,
    "netAssets": 885473150.0,
    "epsTrailingTwelveMonths": 2.4504623,
    "fiftyDayAverageChange": 0.3619995,
    "fiftyDayAverageChangePercent": 0.004155755,
    "twoHundredDayAverageChange": 5.6863174,
    "twoHundredDayAverageChangePercent": 0.06952875,
    "netExpenseRatio": 0.3,
    "sourceInterval": 15,
    "exchangeDataDelayedBy": 15,
    "cryptoTradeable": false,
    "trailingPegRatio": null
}